yeouia/__init__.py
yeouia/apps.py
yeouia/backends.py
yeouia/migrations/__init__.py
yeouia/tests.py
yeouia-4.0.0.dist-info/LICENSE
yeouia-4.0.0.dist-info/WHEEL
yeouia-4.0.0.dist-info/METADATA
yeouia-4.0.0.dist-info/RECORD
