Metadata-Version: 2.1
Name: yeouia
Version: 4.0.0
Summary: Yummy Email Or Username Insensitive Auth model backend for Django
Home-page: https://github.com/nim65s/django-YummyEmailOrUsernameInsensitiveAuth
License: BSD-2-Clause
Author: Guilhem Saurel
Author-email: guilhem.saurel@laas.fr
Requires-Python: >=3.8,<4.0
Classifier: License :: OSI Approved :: BSD License
Classifier: Programming Language :: Python :: 3
Classifier: Programming Language :: Python :: 3.8
Classifier: Programming Language :: Python :: 3.9
Classifier: Programming Language :: Python :: 3.10
Requires-Dist: Django (>=2.2,<5.0)
Project-URL: Repository, https://github.com/nim65s/django-YummyEmailOrUsernameInsensitiveAuth.git
